milatools/__init__.py
milatools/__version__.py
milatools/cli/__init__.py
milatools/cli/__main__.py
milatools/cli/code.py
milatools/cli/commands.py
milatools/cli/init_command.py
milatools/cli/profile.py
milatools/cli/utils.py
milatools/utils/__init__.py
milatools/utils/compute_node.py
milatools/utils/disk_quota.py
milatools/utils/local_v1.py
milatools/utils/local_v2.py
milatools/utils/parallel_progress.py
milatools/utils/remote_v1.py
milatools/utils/remote_v2.py
milatools/utils/runner.py
milatools/utils/vscode_utils.py
milatools-0.1.8.dist-info/METADATA
milatools-0.1.8.dist-info/WHEEL
milatools-0.1.8.dist-info/entry_points.txt
milatools-0.1.8.dist-info/licenses/LICENSE
milatools-0.1.8.dist-info/RECORD
