Metadata-Version: 2.4
Name: milatools
Version: 0.1.8
Summary: Tools to work with the Mila cluster
Author-email: Olivier Breuleux <breuleux@gmail.com>, Fabrice Normandin <fabrice.normandin@gmail.com>
License-Expression: MIT
License-File: LICENSE
Requires-Python: >=3.9
Requires-Dist: blessed>=1.20.0
Requires-Dist: fabric>=3.2.2
Requires-Dist: questionary>=2.0.1
Requires-Dist: rich>=13.9.4
Requires-Dist: sshconf>=0.2.7
Requires-Dist: tqdm>=4.67.1
Requires-Dist: typing-extensions>=4.12.2
